data_stack/__init__.py
data_stack/exception.py
data_stack/dataset/__init__.py
data_stack/dataset/factory.py
data_stack/dataset/iterator.py
data_stack/dataset/meta.py
data_stack/dataset/preprocesor.py
data_stack/dataset/reporting.py
data_stack/dataset/splitter.py
data_stack/io/__init__.py
data_stack/io/resource_definition.py
data_stack/io/resources.py
data_stack/io/retriever.py
data_stack/io/storage_connectors.py
data_stack/mnist/__init__.py
data_stack/mnist/factory.py
data_stack/mnist/iterator.py
data_stack/mnist/preprocessor.py
data_stack/repository/__init__.py
data_stack/repository/repository.py
data_stack/util/__init__.py
data_stack/util/helper.py
data_stack/util/logger.py
datastack-0.0.13.dist-info/METADATA
datastack-0.0.13.dist-info/WHEEL
datastack-0.0.13.dist-info/top_level.txt
datastack-0.0.13.dist-info/RECORD
