Metadata-Version: 2.1
Name: datastack
Version: 0.0.13
Summary: DataStack, a stream based solution for machine learning dataset retrieval and storage
Home-page: https://github.com/le1nux/datastack
Author: Max Luebbering
License: UNKNOWN
Platform: UNKNOWN
Requires-Python: >=3.7
Requires-Dist: pytest
Requires-Dist: pytest-cov
Requires-Dist: torch
Requires-Dist: torchvision
Requires-Dist: tqdm
Requires-Dist: PyYAML
Requires-Dist: scikit-learn
